{
 "custom_fields": [
  {
   "_assign": null, 
   "_comments": null, 
   "_liked_by": null, 
   "_user_tags": null, 
   "allow_on_submit": 0, 
   "bold": 0, 
   "collapsible": 0, 
   "collapsible_depends_on": null, 
   "columns": 0, 
   "creation": "2019-02-11 19:01:59.476683", 
   "default": null, 
   "depends_on": null, 
   "description": null, 
   "docstatus": 0, 
   "dt": "Payment Entry", 
   "fetch_from": null, 
   "fetch_if_empty": 0, 
   "fieldname": "serial_no", 
   "fieldtype": "Data", 
   "hidden": 0, 
   "idx": 49, 
   "ignore_user_permissions": 0, 
   "ignore_xss_filter": 0, 
   "in_global_search": 0, 
   "in_list_view": 0, 
   "in_standard_filter": 0, 
   "insert_after": "reference_no", 
   "label": "Serial No", 
   "modified": "2019-02-11 19:01:59.476683", 
   "modified_by": "m.ismail@salehcars.com", 
   "name": "Payment Entry-serial_no", 
   "no_copy": 0, 
   "options": null, 
   "owner": "m.ismail@salehcars.com", 
   "parent": null, 
   "parentfield": null, 
   "parenttype": null, 
   "permlevel": 0, 
   "precision": "", 
   "print_hide": 0, 
   "print_hide_if_no_value": 0, 
   "print_width": null, 
   "read_only": 0, 
   "report_hide": 0, 
   "reqd": 0, 
   "search_index": 0, 
   "translatable": 1, 
   "unique": 0, 
   "width": null
  }
 ], 
 "custom_perms": [], 
 "doctype": "Payment Entry", 
 "property_setters": [
  {
   "_assign": null, 
   "_comments": null, 
   "_liked_by": null, 
   "_user_tags": null, 
   "creation": "2020-02-01 09:43:25.780304", 
   "default_value": null, 
   "doc_type": "Payment Entry", 
   "docstatus": 0, 
   "doctype_or_field": "DocField", 
   "field_name": "paid_amount", 
   "idx": 0, 
   "modified": "2020-02-01 09:43:25.780304", 
   "modified_by": "awad@salehcars.com", 
   "name": "Payment Entry-paid_amount-in_standard_filter", 
   "owner": "awad@salehcars.com", 
   "parent": null, 
   "parentfield": null, 
   "parenttype": null, 
   "property": "in_standard_filter", 
   "property_type": "Check", 
   "value": "1"
  }, 
  {
   "_assign": null, 
   "_comments": null, 
   "_liked_by": null, 
   "_user_tags": null, 
   "creation": "2020-02-01 09:43:25.728159", 
   "default_value": null, 
   "doc_type": "Payment Entry", 
   "docstatus": 0, 
   "doctype_or_field": "DocType", 
   "field_name": null, 
   "idx": 0, 
   "modified": "2020-02-01 09:43:25.728159", 
   "modified_by": "awad@salehcars.com", 
   "name": "Payment Entry-read_only_onload", 
   "owner": "awad@salehcars.com", 
   "parent": null, 
   "parentfield": null, 
   "parenttype": null, 
   "property": "read_only_onload", 
   "property_type": "Check", 
   "value": null
  }, 
  {
   "_assign": null, 
   "_comments": null, 
   "_liked_by": null, 
   "_user_tags": null, 
   "creation": "2019-12-29 09:49:39.757343", 
   "default_value": null, 
   "doc_type": "Payment Entry", 
   "docstatus": 0, 
   "doctype_or_field": "DocField", 
   "field_name": "mode_of_payment", 
   "idx": 0, 
   "modified": "2019-12-29 09:49:39.757343", 
   "modified_by": "Administrator", 
   "name": "Payment Entry-mode_of_payment-in_list_view", 
   "owner": "Administrator", 
   "parent": null, 
   "parentfield": null, 
   "parenttype": null, 
   "property": "in_list_view", 
   "property_type": "Check", 
   "value": "0"
  }, 
  {
   "_assign": null, 
   "_comments": null, 
   "_liked_by": null, 
   "_user_tags": null, 
   "creation": "2019-12-29 09:48:24.509607", 
   "default_value": null, 
   "doc_type": "Payment Entry", 
   "docstatus": 0, 
   "doctype_or_field": "DocField", 
   "field_name": "paid_amount", 
   "idx": 0, 
   "modified": "2019-12-29 09:48:24.509607", 
   "modified_by": "Administrator", 
   "name": "Payment Entry-paid_amount-in_list_view", 
   "owner": "Administrator", 
   "parent": null, 
   "parentfield": null, 
   "parenttype": null, 
   "property": "in_list_view", 
   "property_type": "Check", 
   "value": "1"
  }, 
  {
   "_assign": null, 
   "_comments": null, 
   "_liked_by": null, 
   "_user_tags": null, 
   "creation": "2019-12-29 09:48:24.494778", 
   "default_value": null, 
   "doc_type": "Payment Entry", 
   "docstatus": 0, 
   "doctype_or_field": "DocField", 
   "field_name": "posting_date", 
   "idx": 0, 
   "modified": "2019-12-29 09:48:24.494778", 
   "modified_by": "Administrator", 
   "name": "Payment Entry-posting_date-in_list_view", 
   "owner": "Administrator", 
   "parent": null, 
   "parentfield": null, 
   "parenttype": null, 
   "property": "in_list_view", 
   "property_type": "Check", 
   "value": "0"
  }, 
  {
   "_assign": null, 
   "_comments": null, 
   "_liked_by": null, 
   "_user_tags": null, 
   "creation": "2019-02-08 09:07:18.524919", 
   "default_value": null, 
   "doc_type": "Payment Entry", 
   "docstatus": 0, 
   "doctype_or_field": "DocField", 
   "field_name": "naming_series", 
   "idx": 0, 
   "modified": "2019-02-08 09:07:18.524919", 
   "modified_by": "Administrator", 
   "name": "Payment Entry-naming_series-options", 
   "owner": "Administrator", 
   "parent": null, 
   "parentfield": null, 
   "parenttype": null, 
   "property": "options", 
   "property_type": "Text", 
   "value": "PE-"
  }
 ], 
 "sync_on_migrate": 1
}